pyRandomWalk/__init__.py
pyRandomWalk/random_walk.py
pyRandomWalk-0.0.1.dist-info/LICENSE
pyRandomWalk-0.0.1.dist-info/METADATA
pyRandomWalk-0.0.1.dist-info/WHEEL
pyRandomWalk-0.0.1.dist-info/top_level.txt
pyRandomWalk-0.0.1.dist-info/RECORD
