Metadata-Version: 2.1
Name: pyRandomWalk
Version: 0.0.1
Summary: Functions for the generation of random walks.
Home-page: https://github.com/AlexanderSouthan/pyRandomWalk
Author: Alexander Southan
Author-email: alexander.southan@web.de
Project-URL: Bug Tracker, https://github.com/AlexanderSouthan/pyRandomWalk/issues
Classifier: Programming Language :: Python :: 3
Classifier: License :: OSI Approved :: MIT License
Classifier: Operating System :: OS Independent
Requires-Python: >=3.6
License-File: LICENSE
Requires-Dist: numpy
Requires-Dist: pandas
Requires-Dist: little-helpers
